LICENSE
goethe/__init__.py
goethe/chapter.py
goethe/content.py
goethe/core.py
goethe/goethe.py
goethe/header.py
goethe/paragraph.py
goethe/section.py
goethe/toctree.py
goethe-0.1.0.dist-info/LICENSE
goethe-0.1.0.dist-info/WHEEL
goethe-0.1.0.dist-info/METADATA
goethe-0.1.0.dist-info/RECORD
