Metadata-Version: 2.1
Name: goethe
Version: 0.1.0
Summary: Create Sphinx RST documents programmatically with Python
Home-page: https://github.com/earthobservations/goethe
License: MIT
Keywords: open-source,RST,restructured-text
Author: Benjamin Gutzmann
Author-email: gutzemann@gmail.com
Requires-Python: >=3.8,<4.0
Classifier: Development Status :: 4 - Beta
Classifier: Intended Audience :: Developers
Classifier: Intended Audience :: Education
Classifier: Intended Audience :: Information Technology
Classifier: Intended Audience :: Science/Research
Classifier: License :: OSI Approved :: MIT License
Classifier: Operating System :: MacOS
Classifier: Operating System :: POSIX
Classifier: Operating System :: Unix
Classifier: Programming Language :: Python
Classifier: Programming Language :: Python :: 3
Classifier: Programming Language :: Python :: 3.8
Classifier: Programming Language :: Python :: 3.9
Classifier: Programming Language :: Python :: 3.10
Classifier: Programming Language :: Python :: 3.11
Classifier: Programming Language :: Python :: 3
Classifier: Programming Language :: Python :: 3.10
Classifier: Programming Language :: Python :: 3.8
Classifier: Programming Language :: Python :: 3.9
Classifier: Topic :: Scientific/Engineering :: Information Analysis
Classifier: Topic :: Scientific/Engineering :: Visualization
Classifier: Topic :: Software Development :: Libraries
Classifier: Topic :: Utilities
Requires-Dist: numpy (>=1.23.4,<2.0.0)
Requires-Dist: rst2pdf (>=0.99,<0.100)
Project-URL: Issues, https://github.com/earthobservations/goethe/issues
Project-URL: Repository, https://github.com/earthobservations/goethe
Project-URL: Releases, https://github.com/earthobservations/goethe/releases
